{"architecture":"amd64","config":{"ExposedPorts":{"80/tcp":{}},"Env":["PATH=/usr/local/sbin:/usr/local/bin:/usr/sbin:/usr/bin:/sbin:/bin"],"Cmd":["nginx","-g","daemon off;"],"Labels":{"org.opencontainers.image.authors":"jamieduncan@google.com","org.opencontainers.image.description":"Containter Fundamentals - Static Website Image","org.opencontainers.image.licenses":"APACHE2","org.opencontainers.image.ref.name":"ubuntu","org.opencontainers.image.source":"https://github.com/jduncan-rva/container-fundamentals","org.opencontainers.image.version":"22.04"},"ArgsEscaped":true,"OnBuild":null},"created":"2023-07-22T10:29:46.9978968Z","history":[{"created":"2023-06-28T08:37:40.107416121Z","created_by":"/bin/sh -c #(nop)  ARG RELEASE","empty_layer":true},{"created":"2023-06-28T08:37:40.172787047Z","created_by":"/bin/sh -c #(nop)  ARG LAUNCHPAD_BUILD_ARCH","empty_layer":true},{"created":"2023-06-28T08:37:40.235648065Z","created_by":"/bin/sh -c #(nop)  LABEL org.opencontainers.image.ref.name=ubuntu","empty_layer":true},{"created":"2023-06-28T08:37:40.292202878Z","created_by":"/bin/sh -c #(nop)  LABEL org.opencontainers.image.version=22.04","empty_layer":true},{"created":"2023-06-28T08:37:42.055763636Z","created_by":"/bin/sh -c #(nop) ADD file:140fb5108b4a2861b5718ad03b4a5174bba03589ea8d4c053e6a0b282f439ff3 in / "},{"created":"2023-06-28T08:37:42.319109064Z","created_by":"/bin/sh -c #(nop)  CMD [\"/bin/bash\"]","empty_layer":true},{"created":"2023-07-22T10:29:19.6780394Z","created_by":"LABEL org.opencontainers.image.authors=jamieduncan@google.com","comment":"buildkit.dockerfile.v0","empty_layer":true},{"created":"2023-07-22T10:29:19.6780394Z","created_by":"LABEL org.opencontainers.image.source=https://github.com/jduncan-rva/container-fundamentals","comment":"buildkit.dockerfile.v0","empty_layer":true},{"created":"2023-07-22T10:29:19.6780394Z","created_by":"LABEL org.opencontainers.image.description=Containter Fundamentals - Static Website Image","comment":"buildkit.dockerfile.v0","empty_layer":true},{"created":"2023-07-22T10:29:19.6780394Z","created_by":"LABEL org.opencontainers.image.licenses=APACHE2","comment":"buildkit.dockerfile.v0","empty_layer":true},{"created":"2023-07-22T10:29:19.6780394Z","created_by":"RUN /bin/sh -c apt update # buildkit","comment":"buildkit.dockerfile.v0"},{"created":"2023-07-22T10:29:46.4815672Z","created_by":"RUN /bin/sh -c apt install nginx -y # buildkit","comment":"buildkit.dockerfile.v0"},{"created":"2023-07-22T10:29:46.7540387Z","created_by":"COPY config/nginx.conf /etc/nginx/ # buildkit","comment":"buildkit.dockerfile.v0"},{"created":"2023-07-22T10:29:46.9978968Z","created_by":"COPY web_content/ /var/www # buildkit","comment":"buildkit.dockerfile.v0"},{"created":"2023-07-22T10:29:46.9978968Z","created_by":"EXPOSE map[80/tcp:{}]","comment":"buildkit.dockerfile.v0","empty_layer":true},{"created":"2023-07-22T10:29:46.9978968Z","created_by":"CMD [\"nginx\" \"-g\" \"daemon off;\"]","comment":"buildkit.dockerfile.v0","empty_layer":true}],"os":"linux","rootfs":{"type":"layers","diff_ids":["sha256:59c56aee1fb4dbaeb334aef06088b49902105d1ea0c15a9e5a2a9ce560fa4c5d","sha256:9728542877234025fed77bf30e834a17460088b1f4a5fc7f24ebee2943a7b435","sha256:192b792ff7bc3f5f016c4ef2f6765f65ffe7fa24549e006b534a7021a3b8a7c5","sha256:cdc82070f3066442d1f072bcc59f6636b6c82f54ec98b046dd50fcc75f91e6fe","sha256:a9a3a90a227350d4451c95cdcf3d95aec51fb3c8d9e23a9cfc9d838fb725084f"]}}